flask_sock/__init__.py
flask_sock-0.7.0.dist-info/LICENSE
flask_sock-0.7.0.dist-info/METADATA
flask_sock-0.7.0.dist-info/WHEEL
flask_sock-0.7.0.dist-info/top_level.txt
flask_sock-0.7.0.dist-info/RECORD
