Metadata-Version: 2.1
Name: flask-sock
Version: 0.7.0
Summary: WebSocket support for Flask
Home-page: https://github.com/miguelgrinberg/flask-sock
Author: Miguel Grinberg
Author-email: miguel.grinberg@gmail.com
Project-URL: Bug Tracker, https://github.com/miguelgrinberg/flask-sock/issues
Classifier: Environment :: Web Environment
Classifier: Intended Audience :: Developers
Classifier: Programming Language :: Python :: 3
Classifier: License :: OSI Approved :: MIT License
Classifier: Operating System :: OS Independent
Requires-Python: >=3.6
License-File: LICENSE
Requires-Dist: flask>=2
Requires-Dist: simple-websocket>=0.5.1
Provides-Extra: docs
Requires-Dist: sphinx; extra == "docs"
